<?xml version="1.0" encoding="UTF-8"?>

<getArtistResponse> 
  <artist>Shakira</artist>  
  <albums> 
    <album>Magia</album>  
    <year>1991</year>  
    <amazonLink>http://www.amazon.com/exec/obidos/redirect?link_code=ur2&amp;tag=wikia-20&amp;camp=1789&amp;creative=9325&amp;path=external-search%3Fsearch-type=ss%26index=music%26keyword=Shakira%20Magia</amazonLink>  
    <songs> 
      <item>Sueños</item>  
      <item>Esta Noche Voy Contigo</item>  
      <item>Lejos De Tu Amor</item>  
      <item>Magia</item>  
      <item>Cuentas Conmigo</item>  
      <item>Cazador De Amor</item>  
      <item>Necesito De Tí</item>  
      <item>Gafas Oscuras</item>  
      <item>Lejos De Tu Amor (Versión Remix)</item> 
    </songs>  
    <album>Peligro</album>  
    <year>1993</year>  
    <amazonLink>http://www.amazon.com/exec/obidos/redirect?link_code=ur2&amp;tag=wikia-20&amp;camp=1789&amp;creative=9325&amp;path=external-search%3Fsearch-type=ss%26index=music%26keyword=Shakira%20Peligro</amazonLink>  
    <songs> 
      <item>Eres</item>  
      <item>Ultimo Momento</item>  
      <item>Tu Seras La Historia De Mi Vida</item>  
      <item>Peligro</item>  
      <item>Quince Años</item>  
      <item>Brujería</item>  
      <item>Eterno Amor</item>  
      <item>Controlas Mi Destino</item>  
      <item>Este Amor Es Lo Mas Bello Del Mundo</item>  
      <item>1968</item> 
    </songs>  
    <album>Pies Descalzos</album>  
    <year>1996</year>  
    <amazonLink>http://www.amazon.com/exec/obidos/redirect?link_code=ur2&amp;tag=wikia-20&amp;camp=1789&amp;creative=9325&amp;path=external-search%3Fsearch-type=ss%26index=music%26keyword=Shakira%20Pies%20Descalzos</amazonLink>  
    <songs> 
      <item>Estoy Aquí</item>  
      <item>Antología</item>  
      <item>Un Poco De Amor</item>  
      <item>Quiero</item>  
      <item>Te Necesito</item>  
      <item>Vuelve</item>  
      <item>Te Espero Sentada</item>  
      <item>Pies Descalzos, Sueños Blancos</item>  
      <item>Pienso En Ti</item>  
      <item>¿Dónde Estás Corazón?</item>  
      <item>Se Quiere, Se Mata</item>  
      <item>Estoy Aquí</item> 
    </songs>  
    <album>The Remixes</album>  
    <year>1997</year>  
    <amazonLink>http://www.amazon.com/exec/obidos/redirect?link_code=ur2&amp;tag=wikia-20&amp;camp=1789&amp;creative=9325&amp;path=external-search%3Fsearch-type=ss%26index=music%26keyword=Shakira%20The%20Remixes</amazonLink>  
    <songs> 
      <item>Shakira DJ Memegamix</item>  
      <item>Estoy Aqui (Rmx)</item>  
      <item>Estou Aqui</item>  
      <item>Donde Estas Corazon (Remix)</item>  
      <item>Un Poco De Amor</item>  
      <item>Um Pouco De Amor</item>  
      <item>Pies Descalzos, Sueños Blancos</item>  
      <item>Pés Descalços</item>  
      <item>Estoy Aquí</item>  
      <item>¿Dónde Estás Corazón?</item>  
      <item>Un Poco De Amor</item>  
      <item>Pies Descalzos, Sueños Blancos</item> 
    </songs>  
    <album>Donde Estan Los Ladrones</album>  
    <year>1998</year>  
    <amazonLink>http://www.amazon.com/exec/obidos/redirect?link_code=ur2&amp;tag=wikia-20&amp;camp=1789&amp;creative=9325&amp;path=external-search%3Fsearch-type=ss%26index=music%26keyword=Shakira%20Donde%20Estan%20Los%20Ladrones</amazonLink>  
    <songs> 
      <item>Ciega, Sordomuda</item>  
      <item>Si Te Vas</item>  
      <item>Moscas En La Casa</item>  
      <item>No Creo</item>  
      <item>Inevitable</item>  
      <item>Octavo Día</item>  
      <item>Que Vuelvas</item>  
      <item>Tú</item>  
      <item>Dónde Están Los Ladrones?</item>  
      <item>La Sombra De Ti</item>  
      <item>Ojos Así</item>  
      <item>Ciega, Sordomuda</item> 
    </songs>  
    <album>MTV Unplugged</album>  
    <year>2000</year>  
    <amazonLink>http://www.amazon.com/exec/obidos/redirect?link_code=ur2&amp;tag=wikia-20&amp;camp=1789&amp;creative=9325&amp;path=external-search%3Fsearch-type=ss%26index=music%26keyword=Shakira%20MTV%20Unplugged</amazonLink>  
    <songs> 
      <item>Octavo Día</item>  
      <item>Si Te Vas</item>  
      <item>Dónde Están Los Ladrones?</item>  
      <item>Moscas En La Casa</item>  
      <item>Ciega, Sordomuda</item>  
      <item>Inevitable</item>  
      <item>Estoy Aquí</item>  
      <item>Tú</item>  
      <item>La Sombra De Ti</item>  
      <item>No Creo</item>  
      <item>Ojos Así</item> 
    </songs>  
    <album>Laundry Service</album>  
    <year>2001</year>  
    <amazonLink>http://www.amazon.com/exec/obidos/redirect?link_code=ur2&amp;tag=wikia-20&amp;camp=1789&amp;creative=9325&amp;path=external-search%3Fsearch-type=ss%26index=music%26keyword=Shakira%20Laundry%20Service</amazonLink>  
    <songs> 
      <item>Objection (Tango)</item>  
      <item>Underneath Your Clothes</item>  
      <item>Whenever, Wherever</item>  
      <item>Rules</item>  
      <item>The One</item>  
      <item>Ready For The Good Times</item>  
      <item>Fool</item>  
      <item>Te Dejo Madrid</item>  
      <item>Poem To A Horse</item>  
      <item>Que Me Quedes Tú</item>  
      <item>Eyes Like Yours (Ojos Asi)</item>  
      <item>Suerte</item>  
      <item>Te Aviso, Te Anuncio (Tango)</item>  
      <item>Whenever, Wherever</item> 
    </songs>  
    <album>The Pepsi EP</album>  
    <year>2003</year>  
    <amazonLink>http://www.amazon.com/exec/obidos/redirect?link_code=ur2&amp;tag=wikia-20&amp;camp=1789&amp;creative=9325&amp;path=external-search%3Fsearch-type=ss%26index=music%26keyword=Shakira%20The%20Pepsi%20EP</amazonLink>  
    <songs> 
      <item>Knock On My Door</item>  
      <item>Pideme El Sol</item>  
      <item>Ask For More</item>  
      <item>Pide Más (Pepsi)</item>  
      <item>Ask For More</item>  
      <item>Inevitable (English Version)</item> 
    </songs>  
    <album>Live &amp; Off The Record</album>  
    <year>2004</year>  
    <amazonLink>http://www.amazon.com/exec/obidos/redirect?link_code=ur2&amp;tag=wikia-20&amp;camp=1789&amp;creative=9325&amp;path=external-search%3Fsearch-type=ss%26index=music%26keyword=Shakira%20Live%20&amp;%20Off%20The%20Record</amazonLink>  
    <songs> 
      <item>Ojos Así</item>  
      <item>Si Te Vas</item>  
      <item>Underneath Your Clothes</item>  
      <item>Ciega, Sordomuda</item>  
      <item>The One</item>  
      <item>Back In Black</item>  
      <item>Tú</item>  
      <item>Poem To A Horse</item>  
      <item>Objection (Tango)</item>  
      <item>Whenever, Wherever</item> 
    </songs>  
    <album>Fijación Oral Vol. 1</album>  
    <year>2005</year>  
    <amazonLink>http://www.amazon.com/exec/obidos/redirect?link_code=ur2&amp;tag=wikia-20&amp;camp=1789&amp;creative=9325&amp;path=external-search%3Fsearch-type=ss%26index=music%26keyword=Shakira%20Fijación%20Oral%20Vol.%201</amazonLink>  
    <songs> 
      <item>En Tus Pupilas</item>  
      <item>La Pared</item>  
      <item>La Tortura</item>  
      <item>Obtener Un Si</item>  
      <item>Día Especial</item>  
      <item>Escondite Inglés</item>  
      <item>No</item>  
      <item>Las De La Intuición</item>  
      <item>Día De Enero</item>  
      <item>Lo Imprescindible</item>  
      <item>La Pared (Versión Acústica)</item>  
      <item>La Tortura (Shaketon Remix)</item>  
      <item>La Tortura</item> 
    </songs>  
    <album>Oral Fixation Vol. 2</album>  
    <year>2005</year>  
    <amazonLink>http://www.amazon.com/exec/obidos/redirect?link_code=ur2&amp;tag=wikia-20&amp;camp=1789&amp;creative=9325&amp;path=external-search%3Fsearch-type=ss%26index=music%26keyword=Shakira%20Oral%20Fixation%20Vol.%202</amazonLink>  
    <songs> 
      <item>How Do You Do</item>  
      <item>Illegal</item>  
      <item>Hips Don't Lie</item>  
      <item>Animal City</item>  
      <item>Don't Bother</item>  
      <item>The Day And The Time</item>  
      <item>Dreams For Plans</item>  
      <item>Hey You</item>  
      <item>Your Embrace</item>  
      <item>Costume Makes The Clown</item>  
      <item>Something</item>  
      <item>Timor</item>  
      <item>La Tortura (Alternate Version)</item>  
      <item>Don't Bother (Jrsnchz Radio Mix)</item>  
      <item>Será, Será</item>  
      <item>Hips Don't Lie (Bamboo - 2006 FIFA World Cup Mix)</item>  
      <item>Don't Bother</item> 
    </songs>  
    <album>Love In The Time Of Cholera EP</album>  
    <year>2008</year>  
    <amazonLink>http://www.amazon.com/exec/obidos/redirect?link_code=ur2&amp;tag=wikia-20&amp;camp=1789&amp;creative=9325&amp;path=external-search%3Fsearch-type=ss%26index=music%26keyword=Shakira%20Love%20In%20The%20Time%20Of%20Cholera%20EP</amazonLink>  
    <songs> 
      <item>Hay Amores</item>  
      <item>La Despedida</item>  
      <item>Pienso En Ti</item> 
    </songs>  
    <album>She Wolf</album>  
    <year>2009</year>  
    <amazonLink>http://www.amazon.com/exec/obidos/redirect?link_code=ur2&amp;tag=wikia-20&amp;camp=1789&amp;creative=9325&amp;path=external-search%3Fsearch-type=ss%26index=music%26keyword=Shakira%20She%20Wolf</amazonLink>  
    <songs> 
      <item>She Wolf</item>  
      <item>Did It Again</item>  
      <item>Long Time</item>  
      <item>Why Wait</item>  
      <item>Good Stuff</item>  
      <item>Men In This Town</item>  
      <item>Gypsy</item>  
      <item>Spy</item>  
      <item>Mon Amour</item>  
      <item>Lo Hecho Está Hecho</item>  
      <item>Años Luz</item>  
      <item>Loba</item>  
      <item>Give It Up To Me</item>  
      <item>She Wolf</item> 
    </songs>  
    <album>Sale El Sol</album>  
    <year>2010</year>  
    <amazonLink>http://www.amazon.com/exec/obidos/redirect?link_code=ur2&amp;tag=wikia-20&amp;camp=1789&amp;creative=9325&amp;path=external-search%3Fsearch-type=ss%26index=music%26keyword=Shakira%20Sale%20El%20Sol</amazonLink>  
    <songs> 
      <item>Sale El Sol</item>  
      <item>Loca (Spanish Version)</item>  
      <item>Antes De Las Seis</item>  
      <item>Gordita</item>  
      <item>Addicted To You</item>  
      <item>Lo Que Más</item>  
      <item>Mariposas</item>  
      <item>Rabiosa</item>  
      <item>Devoción</item>  
      <item>Islands</item>  
      <item>Tu Boca</item>  
      <item>Waka Waka (Esto Es África)</item>  
      <item>Loca</item>  
      <item>Rabiosa (English Version)</item>  
      <item>Waka Waka (This Time For Africa)</item>  
      <item>Gitana</item>  
      <item>Loca (Spanish Version)</item> 
    </songs>  
    <album>Shakira.</album>  
    <year>2014</year>  
    <amazonLink>http://www.amazon.com/exec/obidos/redirect?link_code=ur2&amp;tag=wikia-20&amp;camp=1789&amp;creative=9325&amp;path=external-search%3Fsearch-type=ss%26index=music%26keyword=Shakira%20Shakira.</amazonLink>  
    <songs> 
      <item>Dare (La La La)</item>  
      <item>Can't Remember To Forget You</item>  
      <item>Empire</item>  
      <item>You Don't Care About Me</item>  
      <item>Cut Me Deep</item>  
      <item>Spotlight</item>  
      <item>Broken Record</item>  
      <item>Medicine</item>  
      <item>23</item>  
      <item>The One Thing</item>  
      <item>Nunca Me Acuerdo De Olvidarte</item>  
      <item>Loca Por Ti</item>  
      <item>La La La</item>  
      <item>Chasing Shadows</item>  
      <item>That Way</item>  
      <item>Boig Per Tu</item>  
      <item>La La La (Spanish Version)</item>  
      <item>La La La (Brasil 2014)</item> 
    </songs>  
    <album>Songs Featuring Shakira</album>  
    <year/>  
    <amazonLink>http://www.amazon.com/exec/obidos/redirect?link_code=ur2&amp;tag=wikia-20&amp;camp=1789&amp;creative=9325&amp;path=external-search%3Fsearch-type=ss%26index=music%26keyword=Shakira%20Songs%20Featuring%20Shakira</amazonLink>  
    <songs> 
      <item>Alejandro Sanz:Te Lo Agradezco Pero No</item>  
      <item>Beyoncé:Beautiful Liar</item>  
      <item>Wyclef Jean:King &amp; Queen</item>  
      <item>Miguel Bosé:Si Tú No Vuelves</item>  
      <item>Annie Lennox:Sing</item>  
      <item>Mercedes Sosa:La Maza</item>  
      <item>Pitbull:Get It Started</item>  
      <item>Ivete Sangalo:Dançando</item>  
      <item>Draco Rosa:Blanca Mujer</item> 
    </songs>  
    <album>Other Songs</album>  
    <year/>  
    <amazonLink>http://www.amazon.com/exec/obidos/redirect?link_code=ur2&amp;tag=wikia-20&amp;camp=1789&amp;creative=9325&amp;path=external-search%3Fsearch-type=ss%26index=music%26keyword=Shakira%20Other%20Songs</amazonLink>  
    <songs> 
      <item>Beautiful Liar (Music Video Version)</item>  
      <item>Beautiful Liar (Spanish)</item>  
      <item>Contigo</item>  
      <item>Debajo De Tu Ropa</item>  
      <item>Do It Again</item>  
      <item>Donde Están Los Ladrones?</item>  
      <item>Dude Looks Like A Lady</item>  
      <item>En Cuerpo Y Alma</item>  
      <item>I Need You (Te Necesito, English Version)</item>  
      <item>I'm Here (Estoy Aqui)</item>  
      <item>Je L'aime À Mourir</item>  
      <item>La Tortura (English)</item>  
      <item>Mañana Sin Ti</item>  
      <item>Mi Gordita (Original)</item>  
      <item>Mi Vida</item>  
      <item>No Joke</item>  
      <item>Objection (Afro-Punk Version)</item>  
      <item>Para Amarte</item>  
      <item>Poco De Amor</item>  
      <item>Prefiero</item>  
      <item>Pure Intuition</item>  
      <item>Reglas</item>  
      <item>Santa Baby</item>  
      <item>Se Quiere Se Mata</item>  
      <item>Send Me An Angel</item>  
      <item>Siempre Que, Dondequiera Que</item>  
      <item>Te Regalo (I Give To You)</item>  
      <item>Te Regalo</item>  
      <item>The Border</item>  
      <item>This Time For Africa</item>  
      <item>Tus Gafas Oscuras</item>  
      <item>Why Wait For Later</item> 
    </songs> 
  </albums> 
</getArtistResponse>
